odoo/addons/shopinvader_api_quotation/README.rst
odoo/addons/shopinvader_api_quotation/__init__.py
odoo/addons/shopinvader_api_quotation/__manifest__.py
odoo/addons/shopinvader_api_quotation/i18n/shopinvader_api_quotation.pot
odoo/addons/shopinvader_api_quotation/models/__init__.py
odoo/addons/shopinvader_api_quotation/models/sale_order.py
odoo/addons/shopinvader_api_quotation/readme/CONTRIBUTORS.rst
odoo/addons/shopinvader_api_quotation/readme/CREDITS.rst
odoo/addons/shopinvader_api_quotation/readme/DESCRIPTION.rst
odoo/addons/shopinvader_api_quotation/readme/USAGE.rst
odoo/addons/shopinvader_api_quotation/routers/__init__.py
odoo/addons/shopinvader_api_quotation/routers/cart.py
odoo/addons/shopinvader_api_quotation/routers/quotation.py
odoo/addons/shopinvader_api_quotation/schemas/__init__.py
odoo/addons/shopinvader_api_quotation/schemas/sale.py
odoo/addons/shopinvader_api_quotation/static/description/index.html
odoo/addons/shopinvader_api_quotation/tests/__init__.py
odoo/addons/shopinvader_api_quotation/tests/test_shopinvader_api_quotation.py
odoo_addon_shopinvader_api_quotation-16.0.1.1.0.dist-info/METADATA
odoo_addon_shopinvader_api_quotation-16.0.1.1.0.dist-info/WHEEL
odoo_addon_shopinvader_api_quotation-16.0.1.1.0.dist-info/top_level.txt
odoo_addon_shopinvader_api_quotation-16.0.1.1.0.dist-info/RECORD
