Metadata-Version: 2.1
Name: odoo-addon-shopinvader_api_quotation
Version: 16.0.1.1.0
Summary: Shopinvader Quotation
Home-page: https://github.com/shopinvader/odoo-shopinvader
Author: Akretion
License: AGPL-3
Classifier: Programming Language :: Python
Classifier: Framework :: Odoo
Classifier: Framework :: Odoo :: 16.0
Classifier: License :: OSI Approved :: GNU Affero General Public License v3
Requires-Python: >=3.10
Requires-Dist: extendable-pydantic>=1.0.0
Requires-Dist: fastapi
Requires-Dist: odoo-addon-fastapi<16.1dev,>=16.0dev
Requires-Dist: odoo-addon-sale-cart<16.1dev,>=16.0dev
Requires-Dist: odoo-addon-sale-quotation<16.1dev,>=16.0dev
Requires-Dist: odoo-addon-shopinvader-api-cart<16.1dev,>=16.0dev
Requires-Dist: odoo-addon-shopinvader-api-sale<16.1dev,>=16.0dev
Requires-Dist: odoo-addon-shopinvader-api-security-sale<16.1dev,>=16.0dev
Requires-Dist: odoo-addon-shopinvader-schema-sale<16.1dev,>=16.0dev
Requires-Dist: odoo<16.1dev,>=16.0a
Requires-Dist: pydantic>=2.0.0
